setup.py
pdeclib.egg-info/PKG-INFO
pdeclib.egg-info/SOURCES.txt
pdeclib.egg-info/dependency_links.txt
pdeclib.egg-info/top_level.txt
src/pdeclib.py
src/pilib.py