Metadata-Version: 1.0
Name: pdeclib
Version: 0.3
Summary: Python3.3 Decimal Library
Home-page: http://pypi.python.org/pypi/pdeclib/
Author: Mark H Harris
Author-email: harrismh777@gmail.com
License: UNKNOWN
Platform: UNKNOWN
